Lab1/4bitMagnitudeComp_dataFlow.v
module comp(a,b,aeqb,agtb,altb);
input [3:0] a,b;
output aeqb,agtb,altb;
//reg aeqb,agtb,altb;

assign aeqb=(a[3]^~b[3])&&(a[2]^~b[2])&&(a[1]^~b[1])&&(a[0]^~b[0]);

assign agtb = (a[3]&&~b[3]) || (a[3]^~b[3])&&(a[2]&&~b[2]) || (a[3]^~b[3])&&(a[2]^~b[2])&&(a[1]&&~b[1]) || (a[3]^~b[3])&&(a[2]^~b[2])&&(a[1]^~b[1])&&(a[0]&&~b[0]);

assign altb = (b[3]&&~a[3]) || (b[3]^~a[3])&&(b[2]&&~a[2]) || (b[3]^~a[3])&&(b[2]^~a[2])&&(b[1]&&~a[1]) || (b[3]^~a[3])&&(b[2]^~a[2])&&(b[1]^~a[1])&&(b[0]&&~a[0]);


endmodule

module testbench;
reg [3:0]a,b;
wire f1, f2, f3;

comp c(a,b,f1,f2,f3);

initial
begin

$monitor(,$time,"a=%4b b=%4b f1=%b f2=%b f3=%b",a,b,f1,f2,f3);

#0 a = 4'b0000;
#0 b = 4'b0001;

repeat(8)

#5 a = a+4'b0101;
#5 b = b+4'b1000;
end

initial
begin
$dumpfile("4bitmagnitude.vcd");
$dumpvars();
end

endmodule

Lab1/4bitmagnitude.vcd
$date
	Wed Sep 19 00:17:52 2018
$end
$version
	Icarus Verilog
$end
$timescale
	1s
$end
$scope module testbench $end
$var wire 1 ! f3 $end
$var wire 1 " f2 $end
$var wire 1 # f1 $end
$var reg 4 $ a [3:0] $end
$var reg 4 % b [3:0] $end
$scope module c $end
$var wire 4 & a [3:0] $end
$var wire 1 # aeqb $end
$var wire 1 " agtb $end
$var wire 1 ! altb $end
$var wire 4 ' b [3:0] $end
$upscope $end
$upscope $end
$enddefinitions $end
#0
$dumpvars
b1 '
b0 &
b1 %
b0 $
0#
0"
1!
$end
#5
1"
0!
0#
b101 $
b101 &
#10
b1010 $
b1010 &
#15
b1111 $
b1111 &
#20
b100 $
b100 &
#25
b1001 $
b1001 &
#30
b1110 $
b1110 &
#35
b11 $
b11 &
#40
0!
b1000 $
b1000 &
#45
0"
1!
b1001 %
b1001 '
