Lab1/4bitMagnitudeComp_behav.v
module comp(a,b,aeqb,agtb,altb);
input [3:0] a,b;
output aeqb,agtb,altb;
reg aeqb,agtb,altb;

always @(a or b)
begin
aeqb=0; agtb=0; altb=0;
if(a==b)
aeqb=1;
else if (a>b)

agtb=1;
else
altb=1;
end
endmodule

module testbench;
reg [3:0]a,b;
wire f1, f2, f3;

comp c(a,b,f1,f2,f3);

initial
begin

$monitor(,$time,"a=%4b b=%4b f1=%b f2=%b f3=%b",a,b,f1,f2,f3);

#0 a = 4'b0000;
#0 b = 4'b0001;

repeat(8)

#5 a = a+4'b0101;
#5 b = b+4'b1000;
end

initial
begin
$dumpfile("4bitmagnitude.vcd");
$dumpvars();
end

endmodule

Lab1/4bitmagnitude.vcd
$date
	Wed Sep 19 00:04:37 2018
$end
$version
	Icarus Verilog
$end
$timescale
	1s
$end
$scope module testbench $end
$var wire 1 ! f3 $end
$var wire 1 " f2 $end
$var wire 1 # f1 $end
$var reg 4 $ a [3:0] $end
$var reg 4 % b [3:0] $end
$scope module c $end
$var wire 4 & a [3:0] $end
$var wire 4 ' b [3:0] $end
$var reg 1 # aeqb $end
$var reg 1 " agtb $end
$var reg 1 ! altb $end
$upscope $end
$upscope $end
$enddefinitions $end
#0
$dumpvars
b1 '
b0 &
b1 %
b0 $
0#
0"
1!
$end
#5
1"
0!
b101 $
b101 &
#10
1"
b1010 $
b1010 &
#15
1"
b1111 $
b1111 &
#20
1"
b100 $
b100 &
#25
1"
b1001 $
b1001 &
#30
1"
b1110 $
b1110 &
#35
1"
b11 $
b11 &
#40
1"
b1000 $
b1000 &
#45
1!
0"
b1001 %
b1001 '
