Lab2/fadder_behav.v
/*module fadder_behav(a,b,cin,s,cout);
input [3:0] a, b;
input cin;
output reg temp;
output reg [3:0] s;
output reg cout;
reg temp1,temp2;
integer i;
initial
temp = cin;
always@(a or b)

for(i=0;i<=3;i=i+1)
begin
temp1 = a[i] ^ b[i];
s[i] = temp1 ^ cin;
temp2 = a[i]&b[i];
temp = temp2||(temp1 & temp);

if(i==3) 
begin
cout = temp;
end
end
endmodule*/
/////////////////////////////////////////////

module fadder_behav(a,b,cin,sum,cout);
input [3:0]a,b;
input cin;
output [3:0]sum;
output cout;
reg sum;//need to define a reg for lvalue, sum and cout.else error
reg cout;

always@(*) begin

{cout,sum}=a+b+cin;

end
endmodule


module testbench;
reg [3:0]a,b;
wire [3:0]s;
reg z;
wire c;
fadder_behav fb(a,b,z,s,c);

initial
begin
$dumpfile("fadderBehavioral.vcd");
$dumpvars();
end

initial
$monitor(,$time,"a=%4b,b=%4b,z=%b,s=%4b,c=%b",a,b,z,s,c);
initial        
begin        
    #0 a =  4'b0001;// represents delay
	#0 b =  4'b0010;
	#0 z =  1'b0;
	repeat(8)//repeat the loop 8 times
	#8 a = a + 4'b0001;
	#8 b = b + 4'b0100;
end 
endmodule

Lab2/fadderBehavioral.vcd
$date
	Mon Oct 15 13:55:26 2018
$end
$version
	Icarus Verilog
$end
$timescale
	1s
$end
$scope module testbench $end
$var wire 4 ! s [3:0] $end
$var wire 1 " c $end
$var reg 4 # a [3:0] $end
$var reg 4 $ b [3:0] $end
$var reg 1 % z $end
$scope module fb $end
$var wire 4 & a [3:0] $end
$var wire 4 ' b [3:0] $end
$var wire 1 % cin $end
$var reg 1 " cout $end
$var reg 4 ( sum [3:0] $end
$upscope $end
$upscope $end
$enddefinitions $end
#0
$dumpvars
b11 (
b10 '
b1 &
0%
b10 $
b1 #
0"
b11 !
$end
#8
b100 !
b100 (
b10 #
b10 &
#16
b101 !
b101 (
b11 #
b11 &
#24
b110 !
b110 (
b100 #
b100 &
#32
b111 !
b111 (
b101 #
b101 &
#40
b1000 !
b1000 (
b110 #
b110 &
#48
b1001 !
b1001 (
b111 #
b111 &
#56
b1010 !
b1010 (
b1000 #
b1000 &
#64
b1011 !
b1011 (
b1001 #
b1001 &
#72
b1111 !
b1111 (
b110 $
b110 '
